cstow/__init__.py
cstow/command.py
cstow/config.py
cstow/main.py
cstow/stow.py
cstow/view.py
cstow-1.0.0.dist-info/LICENSE
cstow-1.0.0.dist-info/METADATA
cstow-1.0.0.dist-info/WHEEL
cstow-1.0.0.dist-info/entry_points.txt
cstow-1.0.0.dist-info/RECORD
