Metadata-Version: 2.1
Name: cstow
Version: 1.0.0
Summary: GNU Stow wrapper
Home-page: https://github.com/constkolesnyak/cstow
Author: Konstantin Kolesnyak
Author-email: constkolesnyak@gmail.com
Requires-Python: >=3.11,<4.0
Classifier: Programming Language :: Python :: 3
Classifier: Programming Language :: Python :: 3.11
Requires-Dist: fire (>=0,<1)
Requires-Dist: path (>=16.7.1,<17.0.0)
Requires-Dist: pydantic (>=2.1.1,<3.0.0)
Requires-Dist: rich (>=13.5.2,<14.0.0)
Project-URL: Repository, https://github.com/constkolesnyak/cstow
